mymysql.py
mymysql_mod-0.0.1.dist-info/LICENSE
mymysql_mod-0.0.1.dist-info/METADATA
mymysql_mod-0.0.1.dist-info/WHEEL
mymysql_mod-0.0.1.dist-info/top_level.txt
mymysql_mod-0.0.1.dist-info/RECORD
