Metadata-Version: 2.1
Name: mymysql-mod
Version: 0.0.1
Summary: Simple, compact helper for mysql.connector
Home-page: https://github.com/ejohnfel/mymysql
Author: Eric Johnfelt
Author-email: ejohnfel@hotmail.com
License: UNKNOWN
Project-URL: Bug Tracker, https://github.com/ejohnfel/mymysql/issues
Platform: UNKNOWN
Classifier: Programming Language :: Python :: 3
Classifier: License :: OSI Approved :: MIT License
Classifier: Operating System :: OS Independent
Requires-Python: >=3.0
License-File: LICENSE
